EarthMC/DataHandler.py
EarthMC/Utils.py
EarthMC/__init__.py
EarthMC/Classes/GPS.py
EarthMC/Classes/Nations.py
EarthMC/Classes/Players.py
EarthMC/Classes/Towns.py
EarthMC/Classes/__init__.py
EarthMC/Classes/OAPI/Nation.py
EarthMC/Classes/OAPI/Player.py
EarthMC/Classes/OAPI/Town.py
EarthMC/Classes/OAPI/__init__.py
EarthMC-3.5.0.dist-info/METADATA
EarthMC-3.5.0.dist-info/WHEEL
EarthMC-3.5.0.dist-info/top_level.txt
EarthMC-3.5.0.dist-info/RECORD
