Metadata-Version: 2.1
Name: EarthMC
Version: 3.5.0
Summary: Provides data on people, places and more on the EarthMC Minecraft server.
Home-page: https://github.com/EarthMC-Toolkit/EarthMC-Py
Author: Owen3H
License: MIT
Requires-Dist: requests
Requires-Dist: cachetools
